pymage/__init__.py
pymage/__main__.py
pymage/cli.py
pymage/processor.py
pymage/py.typed
pymage_processor-1.1.1.dist-info/LICENSE
pymage_processor-1.1.1.dist-info/METADATA
pymage_processor-1.1.1.dist-info/WHEEL
pymage_processor-1.1.1.dist-info/entry_points.txt
pymage_processor-1.1.1.dist-info/top_level.txt
pymage_processor-1.1.1.dist-info/RECORD
