Metadata-Version: 2.1
Name: pymage-processor
Version: 1.1.1
Summary: Image processor
Author: Rodrigo Martins
License: MIT
Platform: unixe
Platform: linux
Platform: osx
Platform: cygwin
Platform: win32
Classifier: Programming Language :: Python :: 3.8
Classifier: Programming Language :: Python :: 3.9
Requires-Python: >=3.8
License-File: LICENSE
Requires-Dist: Pillow>=9.3.0
Requires-Dist: altgraph>=0.17.2
Requires-Dist: tk>=0.1.0
Requires-Dist: tqdm
Provides-Extra: testing
Requires-Dist: flake8>=6.0.0; extra == "testing"
Requires-Dist: tox>=4.6.4; extra == "testing"
Requires-Dist: pytest>=7.4.0; extra == "testing"
Requires-Dist: pytest-cov>=4.1.0; extra == "testing"
Requires-Dist: mypy>=1.4.1; extra == "testing"
Requires-Dist: tqdm; extra == "testing"
